altFACS/__init__.py
altFACS/autocontrol.py
altFACS/contours.py
altFACS/control.py
altFACS/counts.py
altFACS/density.py
altFACS/distributions.py
altFACS/experiment.py
altFACS/fluorescence.py
altFACS/hyperlog.py
altFACS/lines.py
altFACS/overlay.py
altFACS/quad.py
altFACS/saturation.py
altFACS/singlets.py
altFACS/thresholds.py
altFACS/tidy.py
altFACS/transforms.py
altFACS/xml.py
altFACS-1.0.8.dist-info/LICENSE
altFACS-1.0.8.dist-info/METADATA
altFACS-1.0.8.dist-info/WHEEL
altFACS-1.0.8.dist-info/top_level.txt
altFACS-1.0.8.dist-info/RECORD
