Metadata-Version: 2.1
Name: altFACS
Version: 1.0.8
Summary: FACS tools for split fluorescent proteins
Home-page: https://github.com/BoHuangLab/altFACS
Author: David Brown
Author-email: david.brown3@ucsf.edu
License: MIT
Platform: UNKNOWN
Classifier: Programming Language :: Python :: 3
Classifier: Programming Language :: Python :: 3.7
Requires-Dist: fcsparser
Requires-Dist: numpy
Requires-Dist: pandas
Requires-Dist: matplotlib
Requires-Dist: pickleshare
Requires-Dist: scipy
